napari_philow/__init__.py
napari_philow/_annotation.py
napari_philow/_data_manager.py
napari_philow/_predict.py
napari_philow/_prediction.py
napari_philow/_selector.py
napari_philow/_train_tf.py
napari_philow/_trainer.py
napari_philow/_utils.py
napari_philow/_utils_legacy.py
napari_philow/napari.yaml
napari_philow/_tests/__init__.py
napari_philow/_tests/test_dock_widget.py
napari_philow/segmentation/__init__.py
napari_philow/segmentation/data_augmentation.py
napari_philow/segmentation/dataset.py
napari_philow/segmentation/loss.py
napari_philow/segmentation/metric.py
napari_philow/segmentation/predict.py
napari_philow/segmentation/train.py
napari_philow/segmentation/utils.py
napari_PHILOW-0.2.0.dist-info/LICENSE
napari_PHILOW-0.2.0.dist-info/METADATA
napari_PHILOW-0.2.0.dist-info/WHEEL
napari_PHILOW-0.2.0.dist-info/entry_points.txt
napari_PHILOW-0.2.0.dist-info/top_level.txt
napari_PHILOW-0.2.0.dist-info/RECORD
