Metadata-Version: 2.1
Name: napari-PHILOW
Version: 0.2.0
Summary: PHILOW is an interactive deep learning-based platform for 3D datasets
Home-page: https://github.com/neurobiology-ut/PHILOW
Author: Hiroki Kawai
Author-email: h.kawai888@gmail.com
License: GPLv3
Project-URL: Bug Tracker, https://github.com/neurobiology-ut/PHILOW/issues
Project-URL: Documentation, https://github.com/neurobiology-ut/PHILOW#README.md
Project-URL: Source Code, https://github.com/neurobiology-ut/PHILOW
Project-URL: User Support, https://github.com/neurobiology-ut/PHILOW/issues
Classifier: Development Status :: 2 - Pre-Alpha
Classifier: Framework :: napari
Classifier: Intended Audience :: Developers
Classifier: Operating System :: OS Independent
Classifier: Programming Language :: Python
Classifier: Programming Language :: Python :: 3
Classifier: Programming Language :: Python :: 3.7
Classifier: Programming Language :: Python :: 3.8
Classifier: Programming Language :: Python :: 3.9
Classifier: Programming Language :: Python :: 3.10
Classifier: License :: OSI Approved :: GNU General Public License v3 (GPLv3)
Classifier: Topic :: Scientific/Engineering :: Image Processing
Requires-Python: >=3.8
License-File: LICENSE
Requires-Dist: numpy
Requires-Dist: scikit-image
Requires-Dist: dask-image
Requires-Dist: opencv-python
Requires-Dist: matplotlib
Requires-Dist: pandas
Requires-Dist: torch
Requires-Dist: torchvision
Requires-Dist: segmentation-models-pytorch
Provides-Extra: testing
Requires-Dist: tox ; extra == 'testing'
Requires-Dist: pytest ; extra == 'testing'
Requires-Dist: pytest-cov ; extra == 'testing'
Requires-Dist: pytest-qt ; extra == 'testing'
Requires-Dist: napari ; extra == 'testing'
Requires-Dist: pyqt5 ; extra == 'testing'
